<?xml version="1.0" encoding="UTF-8"?><record_update table="sys_rest_message_fn">
    <sys_rest_message_fn action="DELETE">
        <authentication_type>no_authentication</authentication_type>
        <basic_auth_password/>
        <basic_auth_profile/>
        <basic_auth_user/>
        <content/>
        <function_name>GetIPInfo</function_name>
        <http_method>get</http_method>
        <lock>false</lock>
        <oauth2_profile/>
        <protocol_name/>
        <qualified_name> IPInfo [ GetIPInfo ]</qualified_name>
        <rest_endpoint>https://ipinfo.io/${ipaddress}/json</rest_endpoint>
        <rest_message display_value=" IPInfo">b8c5383683842210f317cdc6feaad3bb</rest_message>
        <sys_class_name>sys_rest_message_fn</sys_class_name>
        <sys_created_by>admin</sys_created_by>
        <sys_created_on>2025-03-06 13:49:06</sys_created_on>
        <sys_id>eef574f283842210f317cdc6feaad3d9</sys_id>
        <sys_mod_count>6</sys_mod_count>
        <sys_name>GetIPInfo</sys_name>
        <sys_package display_value="IPLookup" source="x_1638214_iplookup">6195fc7e83442210f317cdc6feaad3bd</sys_package>
        <sys_policy/>
        <sys_scope display_value="IPLookup">6195fc7e83442210f317cdc6feaad3bd</sys_scope>
        <sys_update_name>sys_rest_message_fn_eef574f283842210f317cdc6feaad3d9</sys_update_name>
        <sys_updated_by>admin</sys_updated_by>
        <sys_updated_on>2025-03-06 14:31:55</sys_updated_on>
        <use_basic_auth>false</use_basic_auth>
        <use_mid_server/>
        <use_mutual_auth>false</use_mutual_auth>
    </sys_rest_message_fn>
    <sys_update_version action="INSERT_OR_UPDATE">
        <action>DELETE</action>
        <application display_value="IPLookup">6195fc7e83442210f317cdc6feaad3bd</application>
        <file_path/>
        <instance_id>8c649cbb1b6142d878c7cb7b234bcb68</instance_id>
        <instance_name>dev261571</instance_name>
        <name>sys_rest_message_fn_eef574f283842210f317cdc6feaad3d9</name>
        <payload><![CDATA[<?xml version="1.0" encoding="UTF-8"?><record_update table="sys_rest_message_fn"><sys_rest_message_fn action="INSERT_OR_UPDATE"><authentication_type>no_authentication</authentication_type><basic_auth_password/><basic_auth_profile/><basic_auth_user/><content/><function_name>GetIPInfo</function_name><http_method>get</http_method><lock>false</lock><oauth2_profile/><protocol_name/><qualified_name> IPInfo [ GetIPInfo ]</qualified_name><rest_endpoint>https://ipinfo.io/${ipaddress}/json</rest_endpoint><rest_message display_value=" IPInfo">b8c5383683842210f317cdc6feaad3bb</rest_message><sys_class_name>sys_rest_message_fn</sys_class_name><sys_created_by>admin</sys_created_by><sys_created_on>2025-03-06 13:49:06</sys_created_on><sys_id>eef574f283842210f317cdc6feaad3d9</sys_id><sys_mod_count>6</sys_mod_count><sys_name>GetIPInfo</sys_name><sys_package display_value="IPLookup" source="x_1638214_iplookup">6195fc7e83442210f317cdc6feaad3bd</sys_package><sys_policy/><sys_scope display_value="IPLookup">6195fc7e83442210f317cdc6feaad3bd</sys_scope><sys_update_name>sys_rest_message_fn_eef574f283842210f317cdc6feaad3d9</sys_update_name><sys_updated_by>admin</sys_updated_by><sys_updated_on>2025-03-06 14:31:55</sys_updated_on><use_basic_auth>false</use_basic_auth><use_mid_server/><use_mutual_auth>false</use_mutual_auth></sys_rest_message_fn></record_update>]]></payload>
        <payload_hash>490080621</payload_hash>
        <record_name>GetIPInfo</record_name>
        <reverted_from/>
        <source>b195fc7e83442210f317cdc6feaad3c2</source>
        <source_table>sys_update_set</source_table>
        <state>previous</state>
        <sys_created_by>admin</sys_created_by>
        <sys_created_on>2025-03-06 14:31:55</sys_created_on>
        <sys_id>b5cfb87e83842210f317cdc6feaad34f</sys_id>
        <sys_mod_count>0</sys_mod_count>
        <sys_recorded_at>1956bdec30a0000001</sys_recorded_at>
        <sys_updated_by>admin</sys_updated_by>
        <sys_updated_on>2025-03-06 14:31:55</sys_updated_on>
        <type>HTTP Method</type>
        <update_guid>7dcfb87e088422108f1de83a866d254e</update_guid>
        <update_guid_history>7dcfb87e088422108f1de83a866d254e:490080621,0f4bb8bac38422102467fe178ebb4ba0:608601832,eb2b30fad784221098ad887a597b8972:-1824527124,4c1b787aec842210a17fd055636ecbfb:464211018,a3caf47a98842210fe3b75db0e4d6265:2061461629,755834beef4422109e5be8845931fe56:-960119252,2af574f2a7842210371663f4e15632dc:2090849402</update_guid_history>
    </sys_update_version>
    <sys_metadata_delete action="INSERT_OR_UPDATE">
        <sys_audit_delete/>
        <sys_class_name>sys_metadata_delete</sys_class_name>
        <sys_created_by>admin</sys_created_by>
        <sys_created_on>2025-03-06 14:45:12</sys_created_on>
        <sys_db_object display_value="" name="sys_rest_message_fn">sys_rest_message_fn</sys_db_object>
        <sys_id>37309803eb9c492f9657877832779059</sys_id>
        <sys_metadata>eef574f283842210f317cdc6feaad3d9</sys_metadata>
        <sys_mod_count>0</sys_mod_count>
        <sys_name>GetIPInfo</sys_name>
        <sys_package display_value="IPLookup" source="x_1638214_iplookup">6195fc7e83442210f317cdc6feaad3bd</sys_package>
        <sys_parent/>
        <sys_policy/>
        <sys_scope display_value="IPLookup">6195fc7e83442210f317cdc6feaad3bd</sys_scope>
        <sys_scope_delete display_value="">1cd12979d91846bc8d156a5b4e5092d1</sys_scope_delete>
        <sys_update_name>sys_rest_message_fn_eef574f283842210f317cdc6feaad3d9</sys_update_name>
        <sys_update_version display_value="sys_rest_message_fn_eef574f283842210f317cdc6feaad3d9">b5cfb87e83842210f317cdc6feaad34f</sys_update_version>
        <sys_updated_by>admin</sys_updated_by>
        <sys_updated_on>2025-03-06 14:45:12</sys_updated_on>
    </sys_metadata_delete>
</record_update>
